{"columns":[{"title":"id","dataIndex":"id","width":"60px","sorter":true,"key":"id","type":"input","label":"id","placeholder":"Input id"},{"title":"name","dataIndex":"name","width":"60px","sorter":true,"key":"name","type":"input","label":"name","placeholder":"Input name"},{"title":"gender","dataIndex":"gender","width":"60px","sorter":true,"key":"gender","type":"input","label":"gender","placeholder":"Input gender"},{"title":"etnia","dataIndex":"etnia","width":"60px","sorter":true,"key":"etnia","type":"input","label":"etnia","placeholder":"Input etnia"},{"title":"idNumber","dataIndex":"idNumber","width":"60px","sorter":true,"key":"idNumber","type":"input","label":"idNumber","placeholder":"Input idNumber"},{"title":"birthday","dataIndex":"birthday","width":"60px","sorter":true,"key":"birthday","type":"date","label":"birthday","placeholder":"2019-01-01"},{"title":"academicBackground","dataIndex":"academicBackground","width":"60px","sorter":true,"key":"academicBackground","type":"input","label":"academicBackground","placeholder":"Input academicBackground"},{"title":"hrCategory","dataIndex":"hrCategory","width":"60px","sorter":true,"key":"hrCategory","type":"input","label":"hrCategory","placeholder":"Input hrCategory"},{"title":"department","dataIndex":"department","width":"60px","sorter":true,"key":"department","type":"input","label":"department","placeholder":"Input department"},{"title":"workPosition","dataIndex":"workPosition","width":"60px","sorter":true,"key":"workPosition","type":"input","label":"workPosition","placeholder":"Input workPosition"},{"title":"positionAndRank","dataIndex":"positionAndRank","width":"60px","sorter":true,"key":"positionAndRank","type":"input","label":"positionAndRank","placeholder":"Input positionAndRank"},{"title":"militantComission","dataIndex":"militantComission","width":"60px","sorter":true,"key":"militantComission","type":"input","label":"militantComission","placeholder":"Input militantComission"},{"title":"militantRole","dataIndex":"militantRole","width":"60px","sorter":true,"key":"militantRole","type":"input","label":"militantRole","placeholder":"Input militantRole"},{"title":"militantAdmissionDate","dataIndex":"militantAdmissionDate","width":"60px","sorter":true,"key":"militantAdmissionDate","type":"date","label":"militantAdmissionDate","placeholder":"2019-01-01"},{"title":"militantFormalizationDate","dataIndex":"militantFormalizationDate","width":"60px","sorter":true,"key":"militantFormalizationDate","type":"date","label":"militantFormalizationDate","placeholder":"2019-01-01"},{"title":"militanceStatus","dataIndex":"militanceStatus","width":"60px","sorter":true,"key":"militanceStatus","type":"input","label":"militanceStatus","placeholder":"Input militanceStatus"},{"title":"telephone","dataIndex":"telephone","width":"60px","sorter":true,"key":"telephone","type":"input","label":"telephone","placeholder":"Input telephone"},{"title":"homeAddress","dataIndex":"homeAddress","width":"60px","sorter":true,"key":"homeAddress","type":"input","label":"homeAddress","placeholder":"Input homeAddress"},{"title":"looseContact","dataIndex":"looseContact","width":"60px","sorter":true,"key":"looseContact","type":"input","label":"looseContact","placeholder":"Input looseContact"},{"title":"floating","dataIndex":"floating","width":"60px","sorter":true,"key":"floating","type":"input","label":"floating","placeholder":"Input floating"},{"title":"registerDate","dataIndex":"registerDate","width":"60px","sorter":true,"key":"registerDate","type":"date","label":"registerDate","placeholder":"2019-01-01"},{"title":"transferDate","dataIndex":"transferDate","width":"60px","sorter":true,"key":"transferDate","type":"date","label":"transferDate","placeholder":"2019-01-01"},{"title":"user_id","dataIndex":"user_id","width":"60px","sorter":true,"key":"user_id","type":"input","label":"user_id","placeholder":"Input user_id"}]}