{"columns":[{"title":"id","dataIndex":"id","width":"60px","sorter":true,"key":"id","type":"input","label":"id","placeholder":"Input id"},{"title":"title","dataIndex":"title","width":"60px","sorter":true,"key":"title","type":"input","label":"title","placeholder":"Input title"},{"title":"date","dataIndex":"date","width":"60px","sorter":true,"key":"date","type":"date","label":"date","placeholder":"2019-01-01"},{"title":"startTime","dataIndex":"startTime","width":"60px","sorter":true,"key":"startTime","type":"datetime","label":"startTime","placeholder":"12:00:00"},{"title":"duration","dataIndex":"duration","width":"60px","sorter":true,"key":"duration","type":"input","label":"duration","placeholder":"Input duration"},{"title":"applicant","dataIndex":"applicant","width":"60px","sorter":true,"key":"applicant","type":"input","label":"applicant","placeholder":"Input applicant"},{"title":"participants","dataIndex":"participants","width":"60px","sorter":true,"key":"participants","type":"input","label":"participants","placeholder":"Input participants"},{"title":"guests","dataIndex":"guests","width":"60px","sorter":true,"key":"guests","type":"input","label":"guests","placeholder":"Input guests"},{"title":"content","dataIndex":"content","width":"60px","sorter":true,"key":"content","type":"textarea","label":"content","placeholder":"Input content"},{"title":"currentDate","dataIndex":"currentDate","width":"60px","sorter":true,"key":"currentDate","type":"date","label":"currentDate","placeholder":"2019-01-01"},{"title":"reportDate","dataIndex":"reportDate","width":"60px","sorter":true,"key":"reportDate","type":"date","label":"reportDate","placeholder":"2019-01-01"},{"title":"reportContent","dataIndex":"reportContent","width":"60px","sorter":true,"key":"reportContent","type":"input","label":"reportContent","placeholder":"Input reportContent"},{"title":"instructionDate","dataIndex":"instructionDate","width":"60px","sorter":true,"key":"instructionDate","type":"date","label":"instructionDate","placeholder":"2019-01-01"},{"title":"instruction","dataIndex":"instruction","width":"60px","sorter":true,"key":"instruction","type":"input","label":"instruction","placeholder":"Input instruction"},{"title":"priority","dataIndex":"priority","width":"60px","sorter":true,"key":"priority","type":"input","label":"priority","placeholder":"Input priority"},{"title":"user_id","dataIndex":"user_id","width":"60px","sorter":true,"key":"user_id","type":"input","label":"user_id","placeholder":"Input user_id"},{"title":"project_id","dataIndex":"project_id","width":"60px","sorter":true,"key":"project_id","type":"input","label":"project_id","placeholder":"Input project_id"}]}